Workbook

Sheet README
A1: Idea pipeline with written stage gates
A2: Educational only. Not investment advice. Independent; not affiliated with any fund or firm.
A4: One row per idea (Playbook, Play 1). Stages: 0 Inbox, 1 Triage, 2 First read, 3 Deep work, 4 Decision.
A5: Score the four triage criteria 1-5; Score averages them once all four are filled.
A6: Status: Active, Dropped (always fill the drop reason) or Decided.
A7: Summary counts active ideas per stage and warns when more than 3 ideas sit in deep work at once.
A8: Sources shows which idea sources actually reach deep work. Fill the source names you use.
A9: Example rows use FICTIONAL companies.
A10: Educational only. Not investment advice. Independent; not affiliated with any fund or firm.

Sheet Pipeline
A1: Pipeline
A2: Educational only. Not investment advice. Independent; not affiliated with any fund or firm.
A5: Idea | B5: Source | C5: Date entered | D5: Stage (0-4) | E5: Entered stage on | F5: Days in stage | G5: Quality (1-5) | H5: Balance sheet (1-5) | I5: Expectations (1-5) | J5: Angle (1-5) | K5: Score | L5: Why it might be interesting | M5: Status | N5: Drop reason
A6: ExampleCo | B6: Screen: margin change | C6: 46267 | D6: 3 | E6: 46296 | F6: =IF(E6="","",IF(ISNUMBER(E6),TODAY()-E6,IF(ISERROR(DATEVALUE(E6)),"",TODAY()-DATEVALUE(E6)))) | G6: 4 | H6: 3 | I6: 4 | J6: 4 | K6: =IF(COUNT(G6:J6)<4,"",AVERAGE(G6:J6)) | L6: Margins recovering; valuation implies trough margins | M6: Active
A7: SampleCo Logistics | B7: Filing radar: 8-K | C7: 46280 | D7: 2 | E7: 46300 | F7: =IF(E7="","",IF(ISNUMBER(E7),TODAY()-E7,IF(ISERROR(DATEVALUE(E7)),"",TODAY()-DATEVALUE(E7)))) | G7: 3 | H7: 4 | I7: 3 | J7: 2 | K7: =IF(COUNT(G7:J7)<4,"",AVERAGE(G7:J7)) | L7: New multi-year contract disclosed | M7: Active
A8: Demo Retail Group | B8: Reading | C8: 46254 | D8: 1 | E8: 46254 | F8: =IF(E8="","",IF(ISNUMBER(E8),TODAY()-E8,IF(ISERROR(DATEVALUE(E8)),"",TODAY()-DATEVALUE(E8)))) | G8: 2 | H8: 2 | I8: 3 | J8: 2 | K8: =IF(COUNT(G8:J8)<4,"",AVERAGE(G8:J8)) | L8: Store count shrinking, same-store sales unclear | M8: Dropped | N8: No angle; balance sheet weak
A9: Illustrative Software Inc. | B9: Screen: share count down | C9: 46305 | D9: 0 | E9: 46305 | F9: =IF(E9="","",IF(ISNUMBER(E9),TODAY()-E9,IF(ISERROR(DATEVALUE(E9)),"",TODAY()-DATEVALUE(E9)))) | K9: =IF(COUNT(G9:J9)<4,"",AVERAGE(G9:J9)) | L9: Diluted shares down 3 years while revenue grew | M9: Active
F10: =IF(E10="","",IF(ISNUMBER(E10),TODAY()-E10,IF(ISERROR(DATEVALUE(E10)),"",TODAY()-DATEVALUE(E10)))) | K10: =IF(COUNT(G10:J10)<4,"",AVERAGE(G10:J10))
F11: =IF(E11="","",IF(ISNUMBER(E11),TODAY()-E11,IF(ISERROR(DATEVALUE(E11)),"",TODAY()-DATEVALUE(E11)))) | K11: =IF(COUNT(G11:J11)<4,"",AVERAGE(G11:J11))
F12: =IF(E12="","",IF(ISNUMBER(E12),TODAY()-E12,IF(ISERROR(DATEVALUE(E12)),"",TODAY()-DATEVALUE(E12)))) | K12: =IF(COUNT(G12:J12)<4,"",AVERAGE(G12:J12))
F13: =IF(E13="","",IF(ISNUMBER(E13),TODAY()-E13,IF(ISERROR(DATEVALUE(E13)),"",TODAY()-DATEVALUE(E13)))) | K13: =IF(COUNT(G13:J13)<4,"",AVERAGE(G13:J13))
F14: =IF(E14="","",IF(ISNUMBER(E14),TODAY()-E14,IF(ISERROR(DATEVALUE(E14)),"",TODAY()-DATEVALUE(E14)))) | K14: =IF(COUNT(G14:J14)<4,"",AVERAGE(G14:J14))
F15: =IF(E15="","",IF(ISNUMBER(E15),TODAY()-E15,IF(ISERROR(DATEVALUE(E15)),"",TODAY()-DATEVALUE(E15)))) | K15: =IF(COUNT(G15:J15)<4,"",AVERAGE(G15:J15))
F16: =IF(E16="","",IF(ISNUMBER(E16),TODAY()-E16,IF(ISERROR(DATEVALUE(E16)),"",TODAY()-DATEVALUE(E16)))) | K16: =IF(COUNT(G16:J16)<4,"",AVERAGE(G16:J16))
F17: =IF(E17="","",IF(ISNUMBER(E17),TODAY()-E17,IF(ISERROR(DATEVALUE(E17)),"",TODAY()-DATEVALUE(E17)))) | K17: =IF(COUNT(G17:J17)<4,"",AVERAGE(G17:J17))
F18: =IF(E18="","",IF(ISNUMBER(E18),TODAY()-E18,IF(ISERROR(DATEVALUE(E18)),"",TODAY()-DATEVALUE(E18)))) | K18: =IF(COUNT(G18:J18)<4,"",AVERAGE(G18:J18))
F19: =IF(E19="","",IF(ISNUMBER(E19),TODAY()-E19,IF(ISERROR(DATEVALUE(E19)),"",TODAY()-DATEVALUE(E19)))) | K19: =IF(COUNT(G19:J19)<4,"",AVERAGE(G19:J19))
F20: =IF(E20="","",IF(ISNUMBER(E20),TODAY()-E20,IF(ISERROR(DATEVALUE(E20)),"",TODAY()-DATEVALUE(E20)))) | K20: =IF(COUNT(G20:J20)<4,"",AVERAGE(G20:J20))
F21: =IF(E21="","",IF(ISNUMBER(E21),TODAY()-E21,IF(ISERROR(DATEVALUE(E21)),"",TODAY()-DATEVALUE(E21)))) | K21: =IF(COUNT(G21:J21)<4,"",AVERAGE(G21:J21))
... F55: =IF(E55="","",IF(ISNUMBER(E55),TODAY()-E55,IF(ISERROR(DATEVALUE(E55)),"",TODAY()-DATEVALUE(E55)))) | K55: =IF(COUNT(G55:J55)<4,"",AVERAGE(G55:J55))

Sheet Summary
A1: Summary: active ideas by stage
A2: Educational only. Not investment advice. Independent; not affiliated with any fund or firm.
A5: Stage | B5: Name | C5: Active ideas
A6: 0 | B6: Inbox | C6: =COUNTIFS(Pipeline!D6:D55,A6,Pipeline!M6:M55,"Active")
A7: 1 | B7: Triage | C7: =COUNTIFS(Pipeline!D6:D55,A7,Pipeline!M6:M55,"Active")
A8: 2 | B8: First read | C8: =COUNTIFS(Pipeline!D6:D55,A8,Pipeline!M6:M55,"Active")
A9: 3 | B9: Deep work | C9: =COUNTIFS(Pipeline!D6:D55,A9,Pipeline!M6:M55,"Active")
A10: 4 | B10: Decision | C10: =COUNTIFS(Pipeline!D6:D55,A10,Pipeline!M6:M55,"Active")
A12: Deep-work cap (3) | C12: =IF(C9>3,"OVER CAP: finish or drop something","OK")
A13: Dropped ideas | C13: =COUNTIF(Pipeline!M6:M55,"Dropped")
A14: Dropped without a reason | C14: =COUNTIFS(Pipeline!M6:M55,"Dropped",Pipeline!N6:N55,"")

Sheet Sources
A1: Sources: which ones reach deep work?
A2: Educational only. Not investment advice. Independent; not affiliated with any fund or firm.
A5: Source | B5: Ideas entered | C5: Reached stage 3+ | D5: Dropped | E5: Hit rate
A6: Screen: margin change | B6: =IF(A6="","",COUNTIF(Pipeline!B6:B55,A6)) | C6: =IF(A6="","",COUNTIFS(Pipeline!B6:B55,A6,Pipeline!D6:D55,">=3")) | D6: =IF(A6="","",COUNTIFS(Pipeline!B6:B55,A6,Pipeline!M6:M55,"Dropped")) | E6: =IF(OR(A6="",N(B6)=0),"",C6/B6)
A7: Filing radar: 8-K | B7: =IF(A7="","",COUNTIF(Pipeline!B6:B55,A7)) | C7: =IF(A7="","",COUNTIFS(Pipeline!B6:B55,A7,Pipeline!D6:D55,">=3")) | D7: =IF(A7="","",COUNTIFS(Pipeline!B6:B55,A7,Pipeline!M6:M55,"Dropped")) | E7: =IF(OR(A7="",N(B7)=0),"",C7/B7)
A8: Reading | B8: =IF(A8="","",COUNTIF(Pipeline!B6:B55,A8)) | C8: =IF(A8="","",COUNTIFS(Pipeline!B6:B55,A8,Pipeline!D6:D55,">=3")) | D8: =IF(A8="","",COUNTIFS(Pipeline!B6:B55,A8,Pipeline!M6:M55,"Dropped")) | E8: =IF(OR(A8="",N(B8)=0),"",C8/B8)
A9: Screen: share count down | B9: =IF(A9="","",COUNTIF(Pipeline!B6:B55,A9)) | C9: =IF(A9="","",COUNTIFS(Pipeline!B6:B55,A9,Pipeline!D6:D55,">=3")) | D9: =IF(A9="","",COUNTIFS(Pipeline!B6:B55,A9,Pipeline!M6:M55,"Dropped")) | E9: =IF(OR(A9="",N(B9)=0),"",C9/B9)
B10: =IF(A10="","",COUNTIF(Pipeline!B6:B55,A10)) | C10: =IF(A10="","",COUNTIFS(Pipeline!B6:B55,A10,Pipeline!D6:D55,">=3")) | D10: =IF(A10="","",COUNTIFS(Pipeline!B6:B55,A10,Pipeline!M6:M55,"Dropped")) | E10: =IF(OR(A10="",N(B10)=0),"",C10/B10)
B11: =IF(A11="","",COUNTIF(Pipeline!B6:B55,A11)) | C11: =IF(A11="","",COUNTIFS(Pipeline!B6:B55,A11,Pipeline!D6:D55,">=3")) | D11: =IF(A11="","",COUNTIFS(Pipeline!B6:B55,A11,Pipeline!M6:M55,"Dropped")) | E11: =IF(OR(A11="",N(B11)=0),"",C11/B11)
B12: =IF(A12="","",COUNTIF(Pipeline!B6:B55,A12)) | C12: =IF(A12="","",COUNTIFS(Pipeline!B6:B55,A12,Pipeline!D6:D55,">=3")) | D12: =IF(A12="","",COUNTIFS(Pipeline!B6:B55,A12,Pipeline!M6:M55,"Dropped")) | E12: =IF(OR(A12="",N(B12)=0),"",C12/B12)
B13: =IF(A13="","",COUNTIF(Pipeline!B6:B55,A13)) | C13: =IF(A13="","",COUNTIFS(Pipeline!B6:B55,A13,Pipeline!D6:D55,">=3")) | D13: =IF(A13="","",COUNTIFS(Pipeline!B6:B55,A13,Pipeline!M6:M55,"Dropped")) | E13: =IF(OR(A13="",N(B13)=0),"",C13/B13)
B14: =IF(A14="","",COUNTIF(Pipeline!B6:B55,A14)) | C14: =IF(A14="","",COUNTIFS(Pipeline!B6:B55,A14,Pipeline!D6:D55,">=3")) | D14: =IF(A14="","",COUNTIFS(Pipeline!B6:B55,A14,Pipeline!M6:M55,"Dropped")) | E14: =IF(OR(A14="",N(B14)=0),"",C14/B14)
B15: =IF(A15="","",COUNTIF(Pipeline!B6:B55,A15)) | C15: =IF(A15="","",COUNTIFS(Pipeline!B6:B55,A15,Pipeline!D6:D55,">=3")) | D15: =IF(A15="","",COUNTIFS(Pipeline!B6:B55,A15,Pipeline!M6:M55,"Dropped")) | E15: =IF(OR(A15="",N(B15)=0),"",C15/B15)
B16: =IF(A16="","",COUNTIF(Pipeline!B6:B55,A16)) | C16: =IF(A16="","",COUNTIFS(Pipeline!B6:B55,A16,Pipeline!D6:D55,">=3")) | D16: =IF(A16="","",COUNTIFS(Pipeline!B6:B55,A16,Pipeline!M6:M55,"Dropped")) | E16: =IF(OR(A16="",N(B16)=0),"",C16/B16)
B17: =IF(A17="","",COUNTIF(Pipeline!B6:B55,A17)) | C17: =IF(A17="","",COUNTIFS(Pipeline!B6:B55,A17,Pipeline!D6:D55,">=3")) | D17: =IF(A17="","",COUNTIFS(Pipeline!B6:B55,A17,Pipeline!M6:M55,"Dropped")) | E17: =IF(OR(A17="",N(B17)=0),"",C17/B17)
